tracking/__init__.py
tracking/tracker.py
object_tracking-0.1.dist-info/LICENSE
object_tracking-0.1.dist-info/METADATA
object_tracking-0.1.dist-info/WHEEL
object_tracking-0.1.dist-info/top_level.txt
object_tracking-0.1.dist-info/RECORD
