Metadata-Version: 2.1
Name: object-tracking
Version: 0.1
Summary: A simple tracking package for assigning unique IDs to detected objects.
Home-page: https://www.linkedin.com/in/kuntalpal?utm_source=share&utm_campaign=share_via&utm_content=profile&utm_medium=android_app
Author: Kuntal Pal
Author-email: kuntal.pal7550@gmail.com
License: MIT
Keywords: object tracking unique ID assignment
Platform: UNKNOWN
Classifier: Development Status :: 3 - Alpha
Classifier: Intended Audience :: Developers
Classifier: License :: OSI Approved :: MIT License
Classifier: Natural Language :: English
Classifier: Programming Language :: Python
Classifier: Programming Language :: Python :: 3.6
Classifier: Programming Language :: Python :: 3.7
Classifier: Programming Language :: Python :: 3.8
Classifier: Programming Language :: Python :: 3.9
Classifier: Programming Language :: Python :: 3.10
Classifier: Programming Language :: Python :: 3.11
Requires-Dist: numpy>=1.20
Requires-Dist: opencv-python>=4.5.0
